mkdocs_swagger_ui_plugin/__init__.py
mkdocs_swagger_ui_plugin/plugin.py
mkdocs_swagger_ui_html-0.1.1.dist-info/LICENSE
mkdocs_swagger_ui_html-0.1.1.dist-info/METADATA
mkdocs_swagger_ui_html-0.1.1.dist-info/WHEEL
mkdocs_swagger_ui_html-0.1.1.dist-info/entry_points.txt
mkdocs_swagger_ui_html-0.1.1.dist-info/top_level.txt
mkdocs_swagger_ui_html-0.1.1.dist-info/RECORD
