Metadata-Version: 2.1
Name: mkdocs-swagger-ui-html
Version: 0.1.1
Summary: An MkDocs plugin to generate a markdown file containing an API reference built using Swagger UI from a base OAS3 specification.
Home-page: https://github.com/byrnereese/mkdocs-swagger-ui/tree/StructureBreakingChange
Author: Byrne Reese
Author-email: byrne@majordojo.com
License: MIT
Keywords: mkdocs swagger api documentation
Platform: UNKNOWN
Classifier: Development Status :: 4 - Beta
Classifier: Intended Audience :: Developers
Classifier: Intended Audience :: Information Technology
Classifier: License :: OSI Approved :: MIT License
Classifier: Programming Language :: Python
Classifier: Programming Language :: Python :: 3 :: Only
Classifier: Programming Language :: Python :: 3.4
Classifier: Programming Language :: Python :: 3.5
Classifier: Programming Language :: Python :: 3.6
Classifier: Programming Language :: Python :: 3.7
Requires-Python: >=3.0
License-File: LICENSE
Requires-Dist: pyyaml
Requires-Dist: jinja2
Requires-Dist: markdown
Requires-Dist: mkdocs (>=1.0.4)
